[
  {
    "id": "218",
    "title": "The Skyline Problem",
    "href": "https://leetcode.com/problems/the-skyline-problem",
    "difficulty": "Hard",
    "frequency": "100%"
  },
  {
    "id": "307",
    "title": "Range Sum Query - Mutable",
    "href": "https://leetcode.com/problems/range-sum-query-mutable",
    "difficulty": "Medium",
    "frequency": "19.5012%"
  },
  {
    "id": "308",
    "title": "Range Sum Query 2D - Mutable",
    "href": "https://leetcode.com/problems/range-sum-query-2d-mutable",
    "difficulty": "Hard",
    "frequency": "44.0422%"
  },
  {
    "id": "315",
    "title": "Count of Smaller Numbers After Self",
    "href": "https://leetcode.com/problems/count-of-smaller-numbers-after-self",
    "difficulty": "Hard",
    "frequency": "78.5173%"
  },
  {
    "id": "327",
    "title": "Count of Range Sum",
    "href": "https://leetcode.com/problems/count-of-range-sum",
    "difficulty": "Hard",
    "frequency": "53.9763%"
  },
  {
    "id": "493",
    "title": "Reverse Pairs",
    "href": "https://leetcode.com/problems/reverse-pairs",
    "difficulty": "Hard",
    "frequency": "78.5582%"
  }
]