[
  {
    "id": "238",
    "title": "Product of Array Except Self",
    "href": "https://leetcode.com/problems/product-of-array-except-self",
    "difficulty": "Medium",
    "frequency": "2.99893%"
  },
  {
    "id": "202",
    "title": "Happy Number",
    "href": "https://leetcode.com/problems/happy-number",
    "difficulty": "Easy",
    "frequency": "4.40401%"
  },
  {
    "id": "200",
    "title": "Number of Islands",
    "href": "https://leetcode.com/problems/number-of-islands",
    "difficulty": "Medium",
    "frequency": "1.11641%"
  },
  {
    "id": "402",
    "title": "Remove K Digits",
    "href": "https://leetcode.com/problems/remove-k-digits",
    "difficulty": "Medium",
    "frequency": "19.5727%"
  },
  {
    "id": "283",
    "title": "Move Zeroes",
    "href": "https://leetcode.com/problems/move-zeroes",
    "difficulty": "Easy",
    "frequency": "0.789975%"
  },
  {
    "id": "146",
    "title": "LRU Cache",
    "href": "https://leetcode.com/problems/lru-cache",
    "difficulty": "Medium",
    "frequency": "4.37189%"
  },
  {
    "id": "457",
    "title": "Circular Array Loop",
    "href": "https://leetcode.com/problems/circular-array-loop",
    "difficulty": "Medium",
    "frequency": "37.044%"
  },
  {
    "id": "210",
    "title": "Course Schedule II",
    "href": "https://leetcode.com/problems/course-schedule-ii",
    "difficulty": "Medium",
    "frequency": "2.93301%"
  },
  {
    "id": "22",
    "title": "Generate Parentheses",
    "href": "https://leetcode.com/problems/generate-parentheses",
    "difficulty": "Medium",
    "frequency": "0.684049%"
  },
  {
    "id": "76",
    "title": "Minimum Window Substring",
    "href": "https://leetcode.com/problems/minimum-window-substring",
    "difficulty": "Hard",
    "frequency": "0.940928%"
  },
  {
    "id": "208",
    "title": "Implement Trie (Prefix Tree)",
    "href": "https://leetcode.com/problems/implement-trie-prefix-tree",
    "difficulty": "Medium",
    "frequency": "0.675878%"
  },
  {
    "id": "239",
    "title": "Sliding Window Maximum",
    "href": "https://leetcode.com/problems/sliding-window-maximum",
    "difficulty": "Hard",
    "frequency": "0.987975%"
  },
  {
    "id": "826",
    "title": "Most Profit Assigning Work",
    "href": "https://leetcode.com/problems/most-profit-assigning-work",
    "difficulty": "Medium",
    "frequency": "7.51677%"
  },
  {
    "id": "621",
    "title": "Task Scheduler",
    "href": "https://leetcode.com/problems/task-scheduler",
    "difficulty": "Medium",
    "frequency": "4.19159%"
  },
  {
    "id": "207",
    "title": "Course Schedule",
    "href": "https://leetcode.com/problems/course-schedule",
    "difficulty": "Medium",
    "frequency": "0.825498%"
  },
  {
    "id": "33",
    "title": "Search in Rotated Sorted Array",
    "href": "https://leetcode.com/problems/search-in-rotated-sorted-array",
    "difficulty": "Medium",
    "frequency": "3.59212%"
  },
  {
    "id": "55",
    "title": "Jump Game",
    "href": "https://leetcode.com/problems/jump-game",
    "difficulty": "Medium",
    "frequency": "1.46248%"
  },
  {
    "id": "45",
    "title": "Jump Game II",
    "href": "https://leetcode.com/problems/jump-game-ii",
    "difficulty": "Hard",
    "frequency": "41.3911%"
  },
  {
    "id": "991",
    "title": "Broken Calculator",
    "href": "https://leetcode.com/problems/broken-calculator",
    "difficulty": "Medium",
    "frequency": "70.6956%"
  },
  {
    "id": "316",
    "title": "Remove Duplicate Letters",
    "href": "https://leetcode.com/problems/remove-duplicate-letters",
    "difficulty": "Medium",
    "frequency": "0.920965%"
  },
  {
    "id": "1003",
    "title": "Check If Word Is Valid After Substitutions",
    "href": "https://leetcode.com/problems/check-if-word-is-valid-after-substitutions",
    "difficulty": "Medium",
    "frequency": "0%"
  },
  {
    "id": "49",
    "title": "Group Anagrams",
    "href": "https://leetcode.com/problems/group-anagrams",
    "difficulty": "Medium",
    "frequency": "0.274435%"
  },
  {
    "id": "703",
    "title": "Kth Largest Element in a Stream",
    "href": "https://leetcode.com/problems/kth-largest-element-in-a-stream",
    "difficulty": "Easy",
    "frequency": "2.338%"
  },
  {
    "id": "1052",
    "title": "Grumpy Bookstore Owner",
    "href": "https://leetcode.com/problems/grumpy-bookstore-owner",
    "difficulty": "Medium",
    "frequency": "100%"
  },
  {
    "id": "564",
    "title": "Find the Closest Palindrome",
    "href": "https://leetcode.com/problems/find-the-closest-palindrome",
    "difficulty": "Hard",
    "frequency": "6.39924%"
  },
  {
    "id": "403",
    "title": "Frog Jump",
    "href": "https://leetcode.com/problems/frog-jump",
    "difficulty": "Hard",
    "frequency": "16.3338%"
  },
  {
    "id": "1156",
    "title": "Swap For Longest Repeated Character Substring",
    "href": "https://leetcode.com/problems/swap-for-longest-repeated-character-substring",
    "difficulty": "Medium",
    "frequency": "0%"
  },
  {
    "id": "1157",
    "title": "Online Majority Element In Subarray",
    "href": "https://leetcode.com/problems/online-majority-element-in-subarray",
    "difficulty": "Hard",
    "frequency": "0%"
  },
  {
    "id": "460",
    "title": "LFU Cache",
    "href": "https://leetcode.com/problems/lfu-cache",
    "difficulty": "Hard",
    "frequency": "1.98056%"
  },
  {
    "id": "17",
    "title": "Letter Combinations of a Phone Number",
    "href": "https://leetcode.com/problems/letter-combinations-of-a-phone-number",
    "difficulty": "Medium",
    "frequency": "1.15448%"
  },
  {
    "id": "253",
    "title": "Meeting Rooms II",
    "href": "https://leetcode.com/problems/meeting-rooms-ii",
    "difficulty": "Medium",
    "frequency": "1.3197%"
  },
  {
    "id": "40",
    "title": "Combination Sum II",
    "href": "https://leetcode.com/problems/combination-sum-ii",
    "difficulty": "Medium",
    "frequency": "1.53893%"
  },
  {
    "id": "273",
    "title": "Integer to English Words",
    "href": "https://leetcode.com/problems/integer-to-english-words",
    "difficulty": "Hard",
    "frequency": "3.42523%"
  },
  {
    "id": "977",
    "title": "Squares of a Sorted Array",
    "href": "https://leetcode.com/problems/squares-of-a-sorted-array",
    "difficulty": "Easy",
    "frequency": "1.0813%"
  },
  {
    "id": "128",
    "title": "Longest Consecutive Sequence",
    "href": "https://leetcode.com/problems/longest-consecutive-sequence",
    "difficulty": "Hard",
    "frequency": "1.34524%"
  },
  {
    "id": "234",
    "title": "Palindrome Linked List",
    "href": "https://leetcode.com/problems/palindrome-linked-list",
    "difficulty": "Easy",
    "frequency": "1.26428%"
  },
  {
    "id": "5",
    "title": "Longest Palindromic Substring",
    "href": "https://leetcode.com/problems/longest-palindromic-substring",
    "difficulty": "Medium",
    "frequency": "0.59924%"
  },
  {
    "id": "1559",
    "title": "Detect Cycles in 2D Grid",
    "href": "https://leetcode.com/problems/detect-cycles-in-2d-grid",
    "difficulty": "Hard",
    "frequency": "0%"
  },
  {
    "id": "763",
    "title": "Partition Labels",
    "href": "https://leetcode.com/problems/partition-labels",
    "difficulty": "Medium",
    "frequency": "0.462474%"
  },
  {
    "id": "853",
    "title": "Car Fleet",
    "href": "https://leetcode.com/problems/car-fleet",
    "difficulty": "Medium",
    "frequency": "35.0051%"
  }
]