[
  {
    "id": "76",
    "title": "Minimum Window Substring",
    "href": "https://leetcode.com/problems/minimum-window-substring",
    "difficulty": "Hard",
    "frequency": "29.859%"
  },
  {
    "id": "50",
    "title": "Pow(x, n)",
    "href": "https://leetcode.com/problems/powx-n",
    "difficulty": "Medium",
    "frequency": "9.98126%"
  },
  {
    "id": "33",
    "title": "Search in Rotated Sorted Array",
    "href": "https://leetcode.com/problems/search-in-rotated-sorted-array",
    "difficulty": "Medium",
    "frequency": "61.9177%"
  },
  {
    "id": "2",
    "title": "Add Two Numbers",
    "href": "https://leetcode.com/problems/add-two-numbers",
    "difficulty": "Medium",
    "frequency": "23.9293%"
  },
  {
    "id": "39",
    "title": "Combination Sum",
    "href": "https://leetcode.com/problems/combination-sum",
    "difficulty": "Medium",
    "frequency": "3.94088%"
  },
  {
    "id": "146",
    "title": "LRU Cache",
    "href": "https://leetcode.com/problems/lru-cache",
    "difficulty": "Medium",
    "frequency": "100%"
  },
  {
    "id": "108",
    "title": "Convert Sorted Array to Binary Search Tree",
    "href": "https://leetcode.com/problems/convert-sorted-array-to-binary-search-tree",
    "difficulty": "Easy",
    "frequency": "7.59325%"
  },
  {
    "id": "23",
    "title": "Merge k Sorted Lists",
    "href": "https://leetcode.com/problems/merge-k-sorted-lists",
    "difficulty": "Hard",
    "frequency": "28.7385%"
  },
  {
    "id": "116",
    "title": "Populating Next Right Pointers in Each Node",
    "href": "https://leetcode.com/problems/populating-next-right-pointers-in-each-node",
    "difficulty": "Medium",
    "frequency": "14.7645%"
  },
  {
    "id": "322",
    "title": "Coin Change",
    "href": "https://leetcode.com/problems/coin-change",
    "difficulty": "Medium",
    "frequency": "26.4588%"
  },
  {
    "id": "5",
    "title": "Longest Palindromic Substring",
    "href": "https://leetcode.com/problems/longest-palindromic-substring",
    "difficulty": "Medium",
    "frequency": "18.4937%"
  },
  {
    "id": "300",
    "title": "Longest Increasing Subsequence",
    "href": "https://leetcode.com/problems/longest-increasing-subsequence",
    "difficulty": "Medium",
    "frequency": "31.1944%"
  },
  {
    "id": "49",
    "title": "Group Anagrams",
    "href": "https://leetcode.com/problems/group-anagrams",
    "difficulty": "Medium",
    "frequency": "73.0779%"
  },
  {
    "id": "20",
    "title": "Valid Parentheses",
    "href": "https://leetcode.com/problems/valid-parentheses",
    "difficulty": "Easy",
    "frequency": "85.4991%"
  },
  {
    "id": "124",
    "title": "Binary Tree Maximum Path Sum",
    "href": "https://leetcode.com/problems/binary-tree-maximum-path-sum",
    "difficulty": "Hard",
    "frequency": "7.06896%"
  },
  {
    "id": "4",
    "title": "Median of Two Sorted Arrays",
    "href": "https://leetcode.com/problems/median-of-two-sorted-arrays",
    "difficulty": "Hard",
    "frequency": "54.1085%"
  },
  {
    "id": "21",
    "title": "Merge Two Sorted Lists",
    "href": "https://leetcode.com/problems/merge-two-sorted-lists",
    "difficulty": "Easy",
    "frequency": "8.56716%"
  },
  {
    "id": "75",
    "title": "Sort Colors",
    "href": "https://leetcode.com/problems/sort-colors",
    "difficulty": "Medium",
    "frequency": "34.269%"
  },
  {
    "id": "8",
    "title": "String to Integer (atoi)",
    "href": "https://leetcode.com/problems/string-to-integer-atoi",
    "difficulty": "Medium",
    "frequency": "12.3091%"
  },
  {
    "id": "26",
    "title": "Remove Duplicates from Sorted Array",
    "href": "https://leetcode.com/problems/remove-duplicates-from-sorted-array",
    "difficulty": "Easy",
    "frequency": "6.1073%"
  },
  {
    "id": "121",
    "title": "Best Time to Buy and Sell Stock",
    "href": "https://leetcode.com/problems/best-time-to-buy-and-sell-stock",
    "difficulty": "Easy",
    "frequency": "15.256%"
  },
  {
    "id": "297",
    "title": "Serialize and Deserialize Binary Tree",
    "href": "https://leetcode.com/problems/serialize-and-deserialize-binary-tree",
    "difficulty": "Hard",
    "frequency": "11.8829%"
  },
  {
    "id": "47",
    "title": "Permutations II",
    "href": "https://leetcode.com/problems/permutations-ii",
    "difficulty": "Medium",
    "frequency": "17.9393%"
  },
  {
    "id": "1",
    "title": "Two Sum",
    "href": "https://leetcode.com/problems/two-sum",
    "difficulty": "Easy",
    "frequency": "48.1163%"
  },
  {
    "id": "215",
    "title": "Kth Largest Element in an Array",
    "href": "https://leetcode.com/problems/kth-largest-element-in-an-array",
    "difficulty": "Medium",
    "frequency": "9.30139%"
  },
  {
    "id": "460",
    "title": "LFU Cache",
    "href": "https://leetcode.com/problems/lfu-cache",
    "difficulty": "Hard",
    "frequency": "92.5965%"
  },
  {
    "id": "697",
    "title": "Degree of an Array",
    "href": "https://leetcode.com/problems/degree-of-an-array",
    "difficulty": "Easy",
    "frequency": "80.4814%"
  },
  {
    "id": "3",
    "title": "Longest Substring Without Repeating Characters",
    "href": "https://leetcode.com/problems/longest-substring-without-repeating-characters",
    "difficulty": "Medium",
    "frequency": "14.412%"
  },
  {
    "id": "15",
    "title": "3Sum",
    "href": "https://leetcode.com/problems/3sum",
    "difficulty": "Medium",
    "frequency": "7.25278%"
  },
  {
    "id": "46",
    "title": "Permutations",
    "href": "https://leetcode.com/problems/permutations",
    "difficulty": "Medium",
    "frequency": "10.3249%"
  },
  {
    "id": "53",
    "title": "Maximum Subarray",
    "href": "https://leetcode.com/problems/maximum-subarray",
    "difficulty": "Easy",
    "frequency": "2.6059%"
  },
  {
    "id": "62",
    "title": "Unique Paths",
    "href": "https://leetcode.com/problems/unique-paths",
    "difficulty": "Medium",
    "frequency": "6.84402%"
  },
  {
    "id": "63",
    "title": "Unique Paths II",
    "href": "https://leetcode.com/problems/unique-paths-ii",
    "difficulty": "Medium",
    "frequency": "4.73565%"
  },
  {
    "id": "97",
    "title": "Interleaving String",
    "href": "https://leetcode.com/problems/interleaving-string",
    "difficulty": "Hard",
    "frequency": "59.9843%"
  },
  {
    "id": "98",
    "title": "Validate Binary Search Tree",
    "href": "https://leetcode.com/problems/validate-binary-search-tree",
    "difficulty": "Medium",
    "frequency": "11.0063%"
  },
  {
    "id": "206",
    "title": "Reverse Linked List",
    "href": "https://leetcode.com/problems/reverse-linked-list",
    "difficulty": "Easy",
    "frequency": "15.9756%"
  },
  {
    "id": "11",
    "title": "Container With Most Water",
    "href": "https://leetcode.com/problems/container-with-most-water",
    "difficulty": "Medium",
    "frequency": "5.87781%"
  },
  {
    "id": "17",
    "title": "Letter Combinations of a Phone Number",
    "href": "https://leetcode.com/problems/letter-combinations-of-a-phone-number",
    "difficulty": "Medium",
    "frequency": "21.1003%"
  },
  {
    "id": "25",
    "title": "Reverse Nodes in k-Group",
    "href": "https://leetcode.com/problems/reverse-nodes-in-k-group",
    "difficulty": "Hard",
    "frequency": "19.4353%"
  },
  {
    "id": "37",
    "title": "Sudoku Solver",
    "href": "https://leetcode.com/problems/sudoku-solver",
    "difficulty": "Hard",
    "frequency": "83.8661%"
  },
  {
    "id": "56",
    "title": "Merge Intervals",
    "href": "https://leetcode.com/problems/merge-intervals",
    "difficulty": "Medium",
    "frequency": "52.392%"
  },
  {
    "id": "113",
    "title": "Path Sum II",
    "href": "https://leetcode.com/problems/path-sum-ii",
    "difficulty": "Medium",
    "frequency": "4.69347%"
  },
  {
    "id": "151",
    "title": "Reverse Words in a String",
    "href": "https://leetcode.com/problems/reverse-words-in-a-string",
    "difficulty": "Medium",
    "frequency": "6.89524%"
  },
  {
    "id": "155",
    "title": "Min Stack",
    "href": "https://leetcode.com/problems/min-stack",
    "difficulty": "Easy",
    "frequency": "4.15598%"
  },
  {
    "id": "239",
    "title": "Sliding Window Maximum",
    "href": "https://leetcode.com/problems/sliding-window-maximum",
    "difficulty": "Hard",
    "frequency": "5.27954%"
  },
  {
    "id": "243",
    "title": "Shortest Word Distance",
    "href": "https://leetcode.com/problems/shortest-word-distance",
    "difficulty": "Easy",
    "frequency": "16.9891%"
  },
  {
    "id": "255",
    "title": "Verify Preorder Sequence in Binary Search Tree",
    "href": "https://leetcode.com/problems/verify-preorder-sequence-in-binary-search-tree",
    "difficulty": "Medium",
    "frequency": "61.7763%"
  },
  {
    "id": "733",
    "title": "Flood Fill",
    "href": "https://leetcode.com/problems/flood-fill",
    "difficulty": "Easy",
    "frequency": "29.9473%"
  },
  {
    "id": "141",
    "title": "Linked List Cycle",
    "href": "https://leetcode.com/problems/linked-list-cycle",
    "difficulty": "Easy",
    "frequency": "9.32214%"
  },
  {
    "id": "200",
    "title": "Number of Islands",
    "href": "https://leetcode.com/problems/number-of-islands",
    "difficulty": "Medium",
    "frequency": "10.7657%"
  },
  {
    "id": "692",
    "title": "Top K Frequent Words",
    "href": "https://leetcode.com/problems/top-k-frequent-words",
    "difficulty": "Medium",
    "frequency": "1.51954%"
  },
  {
    "id": "234",
    "title": "Palindrome Linked List",
    "href": "https://leetcode.com/problems/palindrome-linked-list",
    "difficulty": "Easy",
    "frequency": "2.13573%"
  },
  {
    "id": "698",
    "title": "Partition to K Equal Sum Subsets",
    "href": "https://leetcode.com/problems/partition-to-k-equal-sum-subsets",
    "difficulty": "Medium",
    "frequency": "7.90792%"
  },
  {
    "id": "153",
    "title": "Find Minimum in Rotated Sorted Array",
    "href": "https://leetcode.com/problems/find-minimum-in-rotated-sorted-array",
    "difficulty": "Medium",
    "frequency": "2.88147%"
  },
  {
    "id": "402",
    "title": "Remove K Digits",
    "href": "https://leetcode.com/problems/remove-k-digits",
    "difficulty": "Medium",
    "frequency": "4.06474%"
  },
  {
    "id": "829",
    "title": "Consecutive Numbers Sum",
    "href": "https://leetcode.com/problems/consecutive-numbers-sum",
    "difficulty": "Hard",
    "frequency": "4.63777%"
  },
  {
    "id": "139",
    "title": "Word Break",
    "href": "https://leetcode.com/problems/word-break",
    "difficulty": "Medium",
    "frequency": "5.88473%"
  },
  {
    "id": "162",
    "title": "Find Peak Element",
    "href": "https://leetcode.com/problems/find-peak-element",
    "difficulty": "Medium",
    "frequency": "5.40928%"
  },
  {
    "id": "295",
    "title": "Find Median from Data Stream",
    "href": "https://leetcode.com/problems/find-median-from-data-stream",
    "difficulty": "Hard",
    "frequency": "36.8206%"
  },
  {
    "id": "621",
    "title": "Task Scheduler",
    "href": "https://leetcode.com/problems/task-scheduler",
    "difficulty": "Medium",
    "frequency": "4.5869%"
  },
  {
    "id": "19",
    "title": "Remove Nth Node From End of List",
    "href": "https://leetcode.com/problems/remove-nth-node-from-end-of-list",
    "difficulty": "Medium",
    "frequency": "1.601%"
  },
  {
    "id": "55",
    "title": "Jump Game",
    "href": "https://leetcode.com/problems/jump-game",
    "difficulty": "Medium",
    "frequency": "6.8459%"
  },
  {
    "id": "268",
    "title": "Missing Number",
    "href": "https://leetcode.com/problems/missing-number",
    "difficulty": "Easy",
    "frequency": "6.3319%"
  },
  {
    "id": "109",
    "title": "Convert Sorted List to Binary Search Tree",
    "href": "https://leetcode.com/problems/convert-sorted-list-to-binary-search-tree",
    "difficulty": "Medium",
    "frequency": "3.06995%"
  },
  {
    "id": "277",
    "title": "Find the Celebrity",
    "href": "https://leetcode.com/problems/find-the-celebrity",
    "difficulty": "Medium",
    "frequency": "40.7128%"
  },
  {
    "id": "426",
    "title": "Convert Binary Search Tree to Sorted Doubly Linked List",
    "href": "https://leetcode.com/problems/convert-binary-search-tree-to-sorted-doubly-linked-list",
    "difficulty": "Medium",
    "frequency": "10.3955%"
  },
  {
    "id": "221",
    "title": "Maximal Square",
    "href": "https://leetcode.com/problems/maximal-square",
    "difficulty": "Medium",
    "frequency": "31.229%"
  },
  {
    "id": "380",
    "title": "Insert Delete GetRandom O(1)",
    "href": "https://leetcode.com/problems/insert-delete-getrandom-o1",
    "difficulty": "Medium",
    "frequency": "7.06557%"
  },
  {
    "id": "525",
    "title": "Contiguous Array",
    "href": "https://leetcode.com/problems/contiguous-array",
    "difficulty": "Medium",
    "frequency": "12.7363%"
  },
  {
    "id": "85",
    "title": "Maximal Rectangle",
    "href": "https://leetcode.com/problems/maximal-rectangle",
    "difficulty": "Hard",
    "frequency": "34.3298%"
  },
  {
    "id": "647",
    "title": "Palindromic Substrings",
    "href": "https://leetcode.com/problems/palindromic-substrings",
    "difficulty": "Medium",
    "frequency": "4.7091%"
  },
  {
    "id": "88",
    "title": "Merge Sorted Array",
    "href": "https://leetcode.com/problems/merge-sorted-array",
    "difficulty": "Easy",
    "frequency": "14.8165%"
  },
  {
    "id": "93",
    "title": "Restore IP Addresses",
    "href": "https://leetcode.com/problems/restore-ip-addresses",
    "difficulty": "Medium",
    "frequency": "67.2316%"
  },
  {
    "id": "238",
    "title": "Product of Array Except Self",
    "href": "https://leetcode.com/problems/product-of-array-except-self",
    "difficulty": "Medium",
    "frequency": "14.7548%"
  },
  {
    "id": "287",
    "title": "Find the Duplicate Number",
    "href": "https://leetcode.com/problems/find-the-duplicate-number",
    "difficulty": "Medium",
    "frequency": "2.13404%"
  },
  {
    "id": "269",
    "title": "Alien Dictionary",
    "href": "https://leetcode.com/problems/alien-dictionary",
    "difficulty": "Hard",
    "frequency": "10.6613%"
  },
  {
    "id": "101",
    "title": "Symmetric Tree",
    "href": "https://leetcode.com/problems/symmetric-tree",
    "difficulty": "Easy",
    "frequency": "2.82219%"
  },
  {
    "id": "186",
    "title": "Reverse Words in a String II",
    "href": "https://leetcode.com/problems/reverse-words-in-a-string-ii",
    "difficulty": "Medium",
    "frequency": "8.73655%"
  },
  {
    "id": "341",
    "title": "Flatten Nested List Iterator",
    "href": "https://leetcode.com/problems/flatten-nested-list-iterator",
    "difficulty": "Medium",
    "frequency": "9.55273%"
  },
  {
    "id": "102",
    "title": "Binary Tree Level Order Traversal",
    "href": "https://leetcode.com/problems/binary-tree-level-order-traversal",
    "difficulty": "Medium",
    "frequency": "4.74864%"
  },
  {
    "id": "706",
    "title": "Design HashMap",
    "href": "https://leetcode.com/problems/design-hashmap",
    "difficulty": "Easy",
    "frequency": "26.8742%"
  },
  {
    "id": "127",
    "title": "Word Ladder",
    "href": "https://leetcode.com/problems/word-ladder",
    "difficulty": "Medium",
    "frequency": "4.54121%"
  },
  {
    "id": "905",
    "title": "Sort Array By Parity",
    "href": "https://leetcode.com/problems/sort-array-by-parity",
    "difficulty": "Easy",
    "frequency": "9.47859%"
  },
  {
    "id": "394",
    "title": "Decode String",
    "href": "https://leetcode.com/problems/decode-string",
    "difficulty": "Medium",
    "frequency": "3.22644%"
  },
  {
    "id": "304",
    "title": "Range Sum Query 2D - Immutable",
    "href": "https://leetcode.com/problems/range-sum-query-2d-immutable",
    "difficulty": "Medium",
    "frequency": "4.01418%"
  },
  {
    "id": "609",
    "title": "Find Duplicate File in System",
    "href": "https://leetcode.com/problems/find-duplicate-file-in-system",
    "difficulty": "Medium",
    "frequency": "22.3273%"
  },
  {
    "id": "347",
    "title": "Top K Frequent Elements",
    "href": "https://leetcode.com/problems/top-k-frequent-elements",
    "difficulty": "Medium",
    "frequency": "2.42004%"
  },
  {
    "id": "199",
    "title": "Binary Tree Right Side View",
    "href": "https://leetcode.com/problems/binary-tree-right-side-view",
    "difficulty": "Medium",
    "frequency": "1.10831%"
  },
  {
    "id": "977",
    "title": "Squares of a Sorted Array",
    "href": "https://leetcode.com/problems/squares-of-a-sorted-array",
    "difficulty": "Easy",
    "frequency": "3.26154%"
  },
  {
    "id": "1328",
    "title": "Break a Palindrome",
    "href": "https://leetcode.com/problems/break-a-palindrome",
    "difficulty": "Medium",
    "frequency": "28.4889%"
  },
  {
    "id": "230",
    "title": "Kth Smallest Element in a BST",
    "href": "https://leetcode.com/problems/kth-smallest-element-in-a-bst",
    "difficulty": "Medium",
    "frequency": "2.69749%"
  },
  {
    "id": "1048",
    "title": "Longest String Chain",
    "href": "https://leetcode.com/problems/longest-string-chain",
    "difficulty": "Medium",
    "frequency": "53.0082%"
  },
  {
    "id": "133",
    "title": "Clone Graph",
    "href": "https://leetcode.com/problems/clone-graph",
    "difficulty": "Medium",
    "frequency": "3.92959%"
  },
  {
    "id": "1209",
    "title": "Remove All Adjacent Duplicates in String II",
    "href": "https://leetcode.com/problems/remove-all-adjacent-duplicates-in-string-ii",
    "difficulty": "Medium",
    "frequency": "3.53109%"
  },
  {
    "id": "226",
    "title": "Invert Binary Tree",
    "href": "https://leetcode.com/problems/invert-binary-tree",
    "difficulty": "Easy",
    "frequency": "4.22771%"
  },
  {
    "id": "416",
    "title": "Partition Equal Subset Sum",
    "href": "https://leetcode.com/problems/partition-equal-subset-sum",
    "difficulty": "Medium",
    "frequency": "2.05296%"
  },
  {
    "id": "28",
    "title": "Implement strStr()",
    "href": "https://leetcode.com/problems/implement-strstr",
    "difficulty": "Easy",
    "frequency": "1.93335%"
  },
  {
    "id": "32",
    "title": "Longest Valid Parentheses",
    "href": "https://leetcode.com/problems/longest-valid-parentheses",
    "difficulty": "Hard",
    "frequency": "2.01045%"
  },
  {
    "id": "36",
    "title": "Valid Sudoku",
    "href": "https://leetcode.com/problems/valid-sudoku",
    "difficulty": "Medium",
    "frequency": "1.48312%"
  },
  {
    "id": "981",
    "title": "Time Based Key-Value Store",
    "href": "https://leetcode.com/problems/time-based-key-value-store",
    "difficulty": "Medium",
    "frequency": "22.4108%"
  },
  {
    "id": "80",
    "title": "Remove Duplicates from Sorted Array II",
    "href": "https://leetcode.com/problems/remove-duplicates-from-sorted-array-ii",
    "difficulty": "Medium",
    "frequency": "3.54262%"
  },
  {
    "id": "720",
    "title": "Longest Word in Dictionary",
    "href": "https://leetcode.com/problems/longest-word-in-dictionary",
    "difficulty": "Easy",
    "frequency": "7.57783%"
  },
  {
    "id": "103",
    "title": "Binary Tree Zigzag Level Order Traversal",
    "href": "https://leetcode.com/problems/binary-tree-zigzag-level-order-traversal",
    "difficulty": "Medium",
    "frequency": "2.76097%"
  },
  {
    "id": "150",
    "title": "Evaluate Reverse Polish Notation",
    "href": "https://leetcode.com/problems/evaluate-reverse-polish-notation",
    "difficulty": "Medium",
    "frequency": "7.13321%"
  },
  {
    "id": "168",
    "title": "Excel Sheet Column Title",
    "href": "https://leetcode.com/problems/excel-sheet-column-title",
    "difficulty": "Easy",
    "frequency": "9.2757%"
  },
  {
    "id": "1451",
    "title": "Rearrange Words in a Sentence",
    "href": "https://leetcode.com/problems/rearrange-words-in-a-sentence",
    "difficulty": "Medium",
    "frequency": "13.8528%"
  }
]